codereport/__init__.py
codereport/cli.py
codereport/codereport.py
codereport/filetree.py
codereport/html.py
codereport/reportitem.py
codereport/templates/base.html
codereport/templates/code_summary.html
codereport/templates/file.html
codereport/templates/index.html
codereport/templates/line.html
codereport/templates/main.html
codereport/templates/style.css
codereport/templates/summary.html
codereport/templates.py
codereport/util.py
codereport-0.4.1.dist-info/LICENSE
codereport-0.4.1.dist-info/METADATA
codereport-0.4.1.dist-info/WHEEL
codereport-0.4.1.dist-info/entry_points.txt
codereport-0.4.1.dist-info/RECORD
