Metadata-Version: 2.3
Name: codereport
Version: 0.4.1
Summary: Make annotated code reports
License: MIT
Author: Paul Gessinger
Author-email: hello@paulgessinger.com
Requires-Python: >=3.8,<4.0
Classifier: License :: OSI Approved :: MIT License
Classifier: Programming Language :: Python :: 3
Classifier: Programming Language :: Python :: 3.8
Classifier: Programming Language :: Python :: 3.9
Classifier: Programming Language :: Python :: 3.10
Classifier: Programming Language :: Python :: 3.11
Classifier: Programming Language :: Python :: 3.12
Classifier: Programming Language :: Python :: 3.13
Requires-Dist: Jinja2 (>=3.1.1,<4.0.0)
Requires-Dist: Pygments (>=2.12.0,<3.0.0)
Requires-Dist: fs (>=2.4.16,<3.0.0)
Requires-Dist: python-slugify (>=6.1.1,<7.0.0)
